{
  "project_info": {
    "project_number": "712853589044",
    "project_id": "cloudlearn-63dc8",
    "storage_bucket": "cloudlearn-63dc8.firebasestorage.app"
  },
  "client": [
    {
      "client_info": {
        "mobilesdk_app_id": "1:712853589044:android:df589b4d5cad50682e0e61",
        "android_client_info": {
          "package_name": "com.example.flut"
        }
      },
      "oauth_client": [],
      "api_key": [
        {
          "current_key": "AIzaSyCMHmhzQ5QHIWLh5pPUls83NaICVdN1IoE"
        }
      ],
      "services": {
        "appinvite_service": {
          "other_platform_oauth_client": []
        }
      }
    }
  ],
  "configuration_version": "1"
}